README.md
setup.py
graze_tropopause.egg-info/PKG-INFO
graze_tropopause.egg-info/SOURCES.txt
graze_tropopause.egg-info/dependency_links.txt
graze_tropopause.egg-info/requires.txt
graze_tropopause.egg-info/top_level.txt
tropopause/__init__.py
tropopause/autoscaling.py
tropopause/cloudformation.py
tropopause/ec2.py
tropopause/elasticloadbalancingv2.py
tropopause/iam.py
tropopause/validators.py