Metadata-Version: 1.2
Name: graze-tropopause
Version: 1.2.0
Summary: lightweight troposphere wrapper
Home-page: https://github.com/graze/tropopause
Author: Graze Developers
Author-email: developers@graze.com
License: The MIT License
Platform: UNKNOWN
Requires-Python: >=3.4
